{
    "summary": "This code instructs the reader to use the graphdb query, implying it is a useful tool for performing queries in this context.",
    "details": [
        {
            "comment": "This code instructs the reader to use the graphdb query, implying it is a useful tool for performing queries in this context.",
            "location": "\"/media/root/Prima/works/generated_docs/lazer_doc/src/multilingual/rockstar/connector/README\":0-0",
            "content": "use the graphdb query. it won't bite."
        }
    ]
}